Metadata-Version: 1.0
Name: lin
Version: 2.6
Summary: a pip-installable package example
Home-page: https://github.com/r4ndompuff/polyhedral_set
Author: Andrey Love
Author-email: r4nd0m1999@gmail.com
License: MIT
Keywords: linear programming,polyhedral set,extreme points
Platform: UNKNOWN
